nootnoot.py
nootnoot-0.0.1.dist-info/LICENSE.txt
nootnoot-0.0.1.dist-info/METADATA
nootnoot-0.0.1.dist-info/WHEEL
nootnoot-0.0.1.dist-info/top_level.txt
nootnoot-0.0.1.dist-info/RECORD
