Metadata-Version: 2.1
Name: nootnoot
Version: 0.0.1
Summary: Noot Noot!
Home-page: UNKNOWN
Author: Michael Kim
Author-email: kim.michael95@gmail.com
License: UNKNOWN
Platform: UNKNOWN
Classifier: Programming Language :: Python :: 3
Classifier: Operating System :: OS Independent
